physdes/__init__.py
physdes/generic.py
physdes/generic.tpy
physdes/interval.py
physdes/merge_obj.py
physdes/point.py
physdes/point.tpy
physdes/polygon.py
physdes/rdllist.py
physdes/recti.py
physdes/rpolygon.py
physdes/skeleton.py
physdes/vector2.py
physdes/vector2.tpy
physdes_py-0.5.dist-info/licenses/LICENSE.txt
physdes_py-0.5.dist-info/METADATA
physdes_py-0.5.dist-info/WHEEL
physdes_py-0.5.dist-info/top_level.txt
physdes_py-0.5.dist-info/RECORD
