Metadata-Version: 2.4
Name: physdes-py
Version: 0.5
Summary: Physical Design Python Code
Home-page: https://github.com/luk036/physdes-py/
Author: Wai-Shing Luk
Author-email: luk036@gmail.com
License: MIT
Project-URL: Documentation, https://pyscaffold.org/
Platform: any
Classifier: Development Status :: 4 - Beta
Classifier: Programming Language :: Python
License-File: LICENSE.txt
Requires-Dist: importlib-metadata; python_version < "3.9"
Requires-Dist: typing_extensions
Requires-Dist: mywheel
Provides-Extra: testing
Requires-Dist: setuptools; extra == "testing"
Requires-Dist: pytest; extra == "testing"
Requires-Dist: pytest-cov; extra == "testing"
Requires-Dist: hypothesis; extra == "testing"
Requires-Dist: typing_extensions; extra == "testing"
Requires-Dist: lds_gen; extra == "testing"
Dynamic: license-file
